tt_tools_common/__init__.py
tt_tools_common/data/__init__.py
tt_tools_common/data/grayskull/axi-pci.yaml
tt_tools_common/data/grayskull/fw_defines.yaml
tt_tools_common/data/grayskull/arc/reset.yaml
tt_tools_common/reset_common/__init__.py
tt_tools_common/reset_common/bh_reset.py
tt_tools_common/reset_common/chip_reset.py
tt_tools_common/reset_common/galaxy_reset.py
tt_tools_common/reset_common/gs_tensix_reset.py
tt_tools_common/reset_common/host_reset_log.py
tt_tools_common/reset_common/reset_utils.py
tt_tools_common/reset_common/wh_reset.py
tt_tools_common/tests/test_bh_reset.py
tt_tools_common/tests/test_detect_fallible.py
tt_tools_common/tests/test_gs_reset.py
tt_tools_common/tests/test_mobo_reset.py
tt_tools_common/tests/test_reset_config.py
tt_tools_common/tests/test_wh_reset.py
tt_tools_common/tests/test_widget_app.py
tt_tools_common/ui_common/__init__.py
tt_tools_common/ui_common/common_style.css
tt_tools_common/ui_common/themes.py
tt_tools_common/ui_common/widgets.py
tt_tools_common/utils_common/__init__.py
tt_tools_common/utils_common/registers.py
tt_tools_common/utils_common/system_utils.py
tt_tools_common/utils_common/tools_utils.py
tt_tools_common-1.5.0.dist-info/licenses/LICENSE
tt_tools_common-1.5.0.dist-info/licenses/LICENSE_understanding.txt
tt_tools_common-1.5.0.dist-info/METADATA
tt_tools_common-1.5.0.dist-info/WHEEL
tt_tools_common-1.5.0.dist-info/top_level.txt
tt_tools_common-1.5.0.dist-info/RECORD
