Metadata-Version: 2.4
Name: tt-tools-common
Version: 1.5.0
Summary: Common library for Tenstorrent tooling
Author-email: Sam Bansal <sbansal@tenstorrent.com>
Maintainer-email: Sam Bansal <sbansal@tenstorrent.com>
License: 
Project-URL: Homepage, http://tenstorrent.com
Project-URL: Bug Reports, https://github.com/tenstorrent/tt-tools-common/issues
Project-URL: Source, https://github.com/tenstorrent/tt-tools-common
Classifier: Development Status :: 4 - Beta
Classifier: Environment :: Console :: Curses
Classifier: License :: OSI Approved :: Apache Software License
Classifier: Programming Language :: Python :: 3
Classifier: Programming Language :: Python :: 3.10
Classifier: Programming Language :: Python :: 3.11
Classifier: Programming Language :: Python :: 3 :: Only
Requires-Python: >=3.10
License-File: LICENSE
License-File: LICENSE_understanding.txt
Requires-Dist: distro>=1.8.0
Requires-Dist: elasticsearch>=8.11.0
Requires-Dist: psutil>=5.9.6
Requires-Dist: pyyaml>=6.0.1
Requires-Dist: rich>=13.7.0
Requires-Dist: textual>=0.59.0
Requires-Dist: requests>=2.32.3
Requires-Dist: tqdm>=4.66.3
Requires-Dist: pydantic>=1.2
Requires-Dist: tomli
Provides-Extra: dev
Requires-Dist: black>=23.11.0; extra == "dev"
Requires-Dist: pre-commit>=3.5.0; extra == "dev"
Requires-Dist: pyluwen~=0.8.0; extra == "dev"
Dynamic: license-file
Dynamic: requires-python
